{"is_source_file": false, "format": "", "description": "", "external_files": [], "external_methods": [], "published": [], "classes": [], "methods": [], "calls": [], "search-terms": [], "state": 2, "file_id": 11, "knowledge_revision": 17, "git_revision": "ba1cdd8a7deec8fa221df2e6b81cc52b6e12d674", "hash": "d001d53c059625c4bcf75bf5a7f3fcf0", "format-version": 4, "code-base-name": "notes_app_frontend", "filename": "notes_app_frontend/package.json", "revision_history": [{"17": "ba1cdd8a7deec8fa221df2e6b81cc52b6e12d674"}]}